MANIFEST.in
README.rst
setup.py
ulang/__init__.py
ulang/__main__.py
ulang/补丁.json
ulang/补丁使用说明.txt
ulang2.egg-info/PKG-INFO
ulang2.egg-info/SOURCES.txt
ulang2.egg-info/dependency_links.txt
ulang2.egg-info/requires.txt
ulang2.egg-info/top_level.txt
ulang/codegen/__init__.py
ulang/codegen/blockly.py
ulang/codegen/python.py
ulang/codegen/ulgen.py
ulang/parser/__init__.py
ulang/parser/core (备用 reserved).pyc
ulang/parser/core.py
ulang/parser/error.py
ulang/parser/lexer.py
ulang/parser/lrparser.py
ulang/parser/parsergenerator.py
ulang/runtime/__init__.py
ulang/runtime/env.py
ulang/runtime/main.py
ulang/runtime/repl.py